{
  "users": [
    {
      "minecraftName": "ansh",
      "minecraftEdition": "Java",
      "wallet": 1000
    },
    {
      "minecraftName": "Billu_backchod",
      "minecraftEdition": "Java",
      "wallet": 1000
    },
    {
      "minecraftName": "minecraft2613",
      "minecraftEdition": "Java",
      "wallet": 1000
    },
    {
      "minecraftName": "billu_backchod",
      "minecraftEdition": "Java",
      "wallet": 1000
    }
  ],
  "lands": [
    {
      "owner": "ansh",
      "coords": [
        {
          "x": 11,
          "y": 1,
          "z": 1
        },
        {
          "x": 1,
          "y": 1,
          "z": 1
        }
      ],
      "blocks": 11,
      "cost": 124.3,
      "baseCost": 110,
      "tax": 11,
      "gst": 3.3,
      "gap": 7,
      "landType": "Player",
      "paymentCode": "Y9QQOC",
      "purchaseTime": 1754395138289,
      "paid": true
    },
    {
      "owner": "ansh",
      "coords": [
        {
          "x": 111,
          "y": 1,
          "z": 22
        },
        {
          "x": 22,
          "y": 1,
          "z": 111
        }
      ],
      "blocks": 8100,
      "cost": 91530,
      "baseCost": 81000,
      "tax": 8100,
      "gst": 2430,
      "gap": 7,
      "landType": "Player",
      "paymentCode": "YO0DD7",
      "purchaseTime": 1754395905517,
      "paid": true
    },
    {
      "owner": "billu_backchod",
      "coords": [
        {
          "x": 150,
          "y": 65,
          "z": -25
        },
        {
          "x": 37,
          "y": 64,
          "z": -99
        }
      ],
      "blocks": 8550,
      "cost": 96615,
      "baseCost": 85500,
      "tax": 8550,
      "gst": 2565,
      "gap": 7,
      "landType": "Player",
      "paymentCode": "R8WG85",
      "purchaseTime": 1754562909381,
      "paid": true
    },
    {
      "owner": "ansh",
      "coords": [
        {
          "x": -4,
          "y": 77,
          "z": -1270
        },
        {
          "x": -250,
          "y": 77,
          "z": -1458
        }
      ],
      "blocks": 46683,
      "cost": 527517.9,
      "baseCost": 466830,
      "tax": 46683,
      "gst": 14004.9,
      "gap": 7,
      "landType": "Player",
      "paymentCode": "49T5LH",
      "purchaseTime": 1754671423014,
      "paid": true
    },
    {
      "owner": "ansh",
      "coords": [
        {
          "x": -372,
          "y": 66,
          "z": 22
        },
        {
          "x": -491,
          "y": 67,
          "z": -79
        }
      ],
      "blocks": 12240,
      "cost": 138312,
      "baseCost": 122400,
      "tax": 12240,
      "gst": 3672,
      "gap": 7,
      "landType": "Player",
      "paymentCode": "6T5YWU",
      "purchaseTime": 1754673532861,
      "paid": true
    },
    {
      "owner": "ansh",
      "coords": [
        {
          "x": -501,
          "y": 105,
          "z": 206
        },
        {
          "x": -480,
          "y": 105,
          "z": 249
        }
      ],
      "blocks": 968,
      "cost": 10938.4,
      "baseCost": 9680,
      "tax": 968,
      "gst": 290.4,
      "gap": 7,
      "landType": "Player",
      "paymentCode": "TNO41G",
      "purchaseTime": 1754673602318,
      "paid": true
    },
    {
      "owner": "ansh",
      "coords": [
        {
          "x": -209,
          "y": 64,
          "z": 1
        },
        {
          "x": -289,
          "y": 66,
          "z": -76
        }
      ],
      "blocks": 6318,
      "cost": 71393.4,
      "baseCost": 63180,
      "tax": 6318,
      "gst": 1895.3999999999999,
      "gap": 7,
      "landType": "Player",
      "paymentCode": "6XU9KB",
      "purchaseTime": 1754673649374,
      "paid": true
    }
  ],
  "govConfig": {
    "gap": 10,
    "landType": "Government"
  },
  "governmentBalance": 936431
}