{
  "users": [],
  "lands": [
    {
      "owner": "ansh",
      "coords": [
        {
          "x": 11,
          "y": 1,
          "z": 11
        },
        {
          "x": 11,
          "y": 1,
          "z": 11
        }
      ],
      "blocks": 1,
      "cost": 24.6,
      "baseCost": 20,
      "tax": 2,
      "gst": 2.6,
      "gap": 7,
      "landType": "Player",
      "paymentCode": "QIJXXG",
      "purchaseTime": 1757089923556,
      "expirationTime": 1757090223556,
      "paid": false
    },
    {
      "owner": "ansh",
      "coords": [
        {
          "x": 222,
          "y": 22,
          "z": 222
        },
        {
          "x": 222,
          "y": 22,
          "z": 222
        }
      ],
      "blocks": 1,
      "cost": 24.6,
      "baseCost": 20,
      "tax": 2,
      "gst": 2.6,
      "gap": 7,
      "landType": "Player",
      "paymentCode": "45XL6R",
      "purchaseTime": 1757090479575,
      "expirationTime": 1757090779575,
      "paid": false
    },
    {
      "owner": "ansh",
      "coords": [
        {
          "x": 33,
          "y": 33,
          "z": 33
        },
        {
          "x": 33,
          "y": 33,
          "z": 33
        }
      ],
      "blocks": 1,
      "cost": 24.6,
      "baseCost": 20,
      "tax": 2,
      "gst": 2.6,
      "gap": 7,
      "landType": "Player",
      "paymentCode": "G359U7",
      "purchaseTime": 1757091144695,
      "expirationTime": 1757091444695,
      "paid": false
    }
  ],
  "govConfig": {
    "gap": 10,
    "landType": "Government"
  },
  "governmentBalance": 0
}