{
  "users": [],
  "lands": [
    {
      "owner": "ansh",
      "coords": [
        {
          "x": 11,
          "y": 1,
          "z": 1
        },
        {
          "x": 1,
          "y": 1,
          "z": 1
        }
      ],
      "blocks": 11,
      "cost": 124.3,
      "baseCost": 110,
      "tax": 11,
      "gst": 3.3,
      "gap": 7,
      "landType": "Player",
      "paymentCode": "ZSR4C3",
      "purchaseTime": 1757087693029,
      "expirationTime": 1757087993029,
      "paid": false
    },
    {
      "owner": "ansh",
      "coords": [
        {
          "x": 111,
          "y": 1,
          "z": 111
        },
        {
          "x": 111,
          "y": 11,
          "z": 111
        }
      ],
      "blocks": 1,
      "cost": 11.3,
      "baseCost": 10,
      "tax": 1,
      "gst": 0.3,
      "gap": 7,
      "landType": "Player",
      "paymentCode": "9WS1N8",
      "purchaseTime": 1757088208338,
      "expirationTime": 1757088508338,
      "paid": false
    },
    {
      "owner": "ansh",
      "coords": [
        {
          "x": 11111,
          "y": 1,
          "z": 111111
        },
        {
          "x": 11111,
          "y": 1,
          "z": 111111
        }
      ],
      "blocks": 1,
      "cost": 11.3,
      "baseCost": 10,
      "tax": 1,
      "gst": 0.3,
      "gap": 7,
      "landType": "Player",
      "paymentCode": "EHFJNR",
      "purchaseTime": 1757088366446,
      "expirationTime": 1757088666446,
      "paid": false
    },
    {
      "owner": "ansh",
      "coords": [
        {
          "x": 222,
          "y": 2,
          "z": 222
        },
        {
          "x": 222,
          "y": 22,
          "z": 22
        }
      ],
      "blocks": 201,
      "cost": 2271.3,
      "baseCost": 2010,
      "tax": 201,
      "gst": 60.3,
      "gap": 7,
      "landType": "Player",
      "paymentCode": "9OQSSO",
      "purchaseTime": 1757088392847,
      "expirationTime": 1757088692847,
      "paid": false
    }
  ],
  "govConfig": {
    "gap": 10,
    "landType": "Government"
  },
  "governmentBalance": 0
}