{
  "users": [
    {
      "minecraftName": "ansh",
      "minecraftEdition": "Java",
      "wallet": 1000
    },
    {
      "minecraftName": "minecraft2613",
      "minecraftEdition": "Java",
      "wallet": 1000
    }
  ],
  "lands": [
    {
      "owner": "ansh",
      "coords": [
        {
          "x": 11,
          "y": 1111,
          "z": 11
        },
        {
          "x": 11,
          "y": 11,
          "z": 11
        },
        {
          "x": 11,
          "y": 11,
          "z": 11
        },
        {
          "x": 11,
          "y": 1111,
          "z": 1111
        }
      ],
      "blocks": 1101,
      "cost": 12441.3,
      "gap": 7,
      "landType": "Player",
      "paymentCode": "4BADA3",
      "purchaseTime": 1754325082959,
      "paid": true
    },
    {
      "owner": "ansh",
      "coords": [
        {
          "x": 87,
          "y": 67,
          "z": 224
        },
        {
          "x": 87,
          "y": 67,
          "z": 229
        },
        {
          "x": 93,
          "y": 67,
          "z": 229
        },
        {
          "x": 93,
          "y": 67,
          "z": 223
        }
      ],
      "blocks": 0,
      "cost": 0,
      "gap": 0,
      "landType": "Player",
      "paymentCode": null,
      "purchaseTime": 1754325136183,
      "paid": true
    },
    {
      "owner": "ansh",
      "coords": [
        {
          "x": 74,
          "y": 71,
          "z": 185
        },
        {
          "x": 84,
          "y": 71,
          "z": 185
        },
        {
          "x": 85,
          "y": 71,
          "z": 146
        },
        {
          "x": 73,
          "y": 71,
          "z": 146
        }
      ],
      "blocks": 0,
      "cost": 0,
      "gap": 0,
      "landType": "Player",
      "paymentCode": null,
      "purchaseTime": 1754325354524,
      "paid": true
    }
  ],
  "govConfig": {
    "gap": 10,
    "landType": "Government"
  },
  "governmentBalance": 12441.3
}